{
  "family": "fez",
  "containerDefinitions": [
    {
      "name": "nginx",
      "image": "uqlibrary/docker-nginx:5",
      "cpu": 128,
      "memory": 256,
      "portMappings": [
        {
          "hostPort": 8006,
          "containerPort": 80,
          "protocol": "tcp"
        }
      ],
      "links": [
        "fpm:fpm"
      ],
      "volumesFrom": [
        {
          "sourceContainer": "fpm"
        }
      ],
      "essential": true
    },
    {
      "name": "fpm",
      "image": "uql-registry.library.uq.edu.au/production/fez:<COMMIT_HASH>",
      "cpu": 256,
      "memory": 1024,
      "environment": [
        {
          "name": "APP_ENVIRONMENT",
          "value": "production"
        },
        {
          "name": "NEWRELIC_LICENSE",
          "value": "<NEWRELIC_LICENSE>"
        },
        {
          "name": "WEBCRON_TOKEN",
          "value": "<WEBCRON_TOKEN>"
        }
      ],
      "mountPoints": [
        {
          "sourceVolume": "templates_c",
          "containerPath": "/var/app/templates_c"
        },
        {
          "sourceVolume": "tmp",
          "containerPath": "/var/app/tmp"
        }
      ],
      "essential": true
    }
  ],
  "volumes": [{
    "name": "templates_c",
    "host": {}
    },{
    "name": "tmp",
    "host": {}
    }]
}